classreg/__init__.py
classreg/mod.py
classreg-0.0.2.dist-info/License.txt
classreg-0.0.2.dist-info/METADATA
classreg-0.0.2.dist-info/WHEEL
classreg-0.0.2.dist-info/top_level.txt
classreg-0.0.2.dist-info/RECORD
